Metadata-Version: 2.1
Name: GeneradorContrasenas
Version: 1.3
Summary: Generador de una o varias contraseñas personalizadas en base a los requisitos especificados por el usuario
Home-page: https://github.com/nereabarrueta/GeneradorContrasenas
Download-URL: https://github.com/nereabarrueta/GeneradorContrasenas/archive/refs/tags/V05.tar.gz
Author: Nerea Barrueta & Alba Vilches
Author-email: nerea.barrueta@alumni.mondragon.edu
License: MIT
Keywords: Generar,Contrasena,Seguridad
Classifier: Development Status :: 5 - Production/Stable
Classifier: Intended Audience :: Developers
Classifier: Topic :: Software Development :: Build Tools
Classifier: License :: OSI Approved :: MIT License
Classifier: Programming Language :: Python :: 3
Classifier: Programming Language :: Python :: 3.4
Classifier: Programming Language :: Python :: 3.5
Classifier: Programming Language :: Python :: 3.6
Classifier: Programming Language :: Python :: 3.7
Classifier: Programming Language :: Python :: 3.8
License-File: LICENSE.txt
